c2dll/__init__.py
c2dll/main.py
c2dll-0.1.0.dist-info/LICENSE
c2dll-0.1.0.dist-info/METADATA
c2dll-0.1.0.dist-info/WHEEL
c2dll-0.1.0.dist-info/top_level.txt
c2dll-0.1.0.dist-info/RECORD
