Metadata-Version: 2.1
Name: c2dll
Version: 0.1.0
Summary: Easily build C code into dll and call it from python script
Author-email: Vladimir Chigarev <chiga17@gmail.com>
Project-URL: Homepage, https://github.com/chiga17/c2dll
Project-URL: Issues, https://github.com/chiga17/c2dll/issues
Classifier: Programming Language :: Python :: 3
Classifier: License :: OSI Approved :: MIT License
Classifier: Operating System :: Microsoft :: Windows
Requires-Python: >=3.8
License-File: LICENSE
